layeredimage/__init__.py
layeredimage/io/__init__.py
layeredimage/io/common.py
layeredimage/io/gif.py
layeredimage/io/layered.py
layeredimage/io/lsr.py
layeredimage/io/ora.py
layeredimage/io/pdn.py
layeredimage/io/psd.py
layeredimage/io/tiff.py
layeredimage/io/webp.py
layeredimage/io/xcf.py
layeredimage/layeredimage.py
layeredimage/layergroup.py
layeredimage-2024.3.dist-info/LICENSE.md
layeredimage-2024.3.dist-info/METADATA
layeredimage-2024.3.dist-info/WHEEL
layeredimage-2024.3.dist-info/RECORD
