Metadata-Version: 2.1
Name: layeredimage
Version: 2024.3
Summary: Use this module to read, and write to a number of layered image formats
Home-page: https://github.com/FHPythonUtils/LayeredImage
License: MIT
Author: FredHappyface
Requires-Python: >=3.9,<4.0
Classifier: Development Status :: 5 - Production/Stable
Classifier: Environment :: Console
Classifier: Intended Audience :: Developers
Classifier: Intended Audience :: Education
Classifier: License :: OSI Approved :: MIT License
Classifier: Natural Language :: English
Classifier: Operating System :: OS Independent
Classifier: Programming Language :: Python :: 3
Classifier: Programming Language :: Python :: 3.9
Classifier: Programming Language :: Python :: 3.10
Classifier: Programming Language :: Python :: 3.11
Classifier: Programming Language :: Python :: 3.12
Classifier: Programming Language :: Python :: Implementation :: CPython
Classifier: Topic :: Multimedia :: Graphics
Classifier: Topic :: Software Development :: Libraries :: Python Modules
Classifier: Topic :: Utilities
Requires-Dist: blendmodes (>=2024.1.1,<2026)
Requires-Dist: gimpformats (>=2024,<2026)
Requires-Dist: loguru (>=0.7.2,<2)
Requires-Dist: pillow (>=10.2.0,<11)
Requires-Dist: psd-tools (>=1.9.31,<2)
Requires-Dist: pylsr (>=2024,<2026)
Requires-Dist: pyora (>=0.3.11,<2)
Requires-Dist: pypdn (>=1.0.6,<2)
Project-URL: Documentation, https://github.com/FHPythonUtils/LayeredImage/blob/master/README.md
Project-URL: Repository, https://github.com/FHPythonUtils/LayeredImage
